sema_protocol/__init__.py
sema_protocol/core.py
sema_protocol/domains.py
sema_protocol/jis_integration.py
sema_protocol/translate.py
sema_protocol-0.1.0.dist-info/METADATA
sema_protocol-0.1.0.dist-info/WHEEL
sema_protocol-0.1.0.dist-info/RECORD
