Metadata-Version: 2.4
Name: sema-protocol
Version: 0.1.0
Summary: Semantic Meaning & Agreement Protocol. The missing layer for global AI coordination. Because 'fraud' in Amsterdam ≠ 'fraud' in Johannesburg.
Project-URL: Homepage, https://humotica.com
Project-URL: Documentation, https://github.com/Humotica/sema-protocol
Project-URL: Repository, https://github.com/Humotica/sema-protocol
Author-email: Jasper van de Meent <jasper@humotica.com>, Root AI <root_ai@humotica.nl>
License-Expression: AGPL-3.0-or-later
Keywords: ai-coordination,appi,banking,compliance,cross-border,fraud-detection,gdpr,humotica,jis,popia,protocol,semantic
Classifier: Development Status :: 3 - Alpha
Classifier: Intended Audience :: Developers
Classifier: Intended Audience :: Financial and Insurance Industry
Classifier: License :: OSI Approved :: GNU Affero General Public License v3 or later (AGPLv3+)
Classifier: Programming Language :: Python :: 3
Classifier: Programming Language :: Python :: 3.10
Classifier: Programming Language :: Python :: 3.11
Classifier: Programming Language :: Python :: 3.12
Classifier: Topic :: Office/Business :: Financial
Classifier: Topic :: Scientific/Engineering :: Artificial Intelligence
Requires-Python: >=3.10
Provides-Extra: jis
Requires-Dist: jis>=0.1.0; extra == 'jis'
